<beans xmlns="http://www.springframework.org/schema/beans"
	xmlns:xsi="http://www.w3.org/2001/XMLSchema-instance" xmlns:context="http://www.springframework.org/schema/context"
	xsi:schemaLocation="http://www.springframework.org/schema/beans
	http://www.springframework.org/schema/beans/spring-beans-2.5.xsd
	http://www.springframework.org/schema/context
	http://www.springframework.org/schema/context/spring-context-2.5.xsd">
	
	<bean id="credentials" class="calculation.expenese.monthly.PageObjects.LoginObjects">
		<property name="wmUserName" value="Mkyong" />
		<property name="wmPassWord" value="Mkyong" />
		<property name="wmLoginBtn" value="Mkyong" />
		<property name="spectrumUserName" value="Mkyong" />
		<property name="spectrumPassWord" value="Mkyong" />
		<property name="spectrumLoginBtn" value="Mkyong" />
		<property name="EngyCoopUserName" value="Mkyong" />
		<property name="EngyCoopPassWord" value="Mkyong" />
		<property name="EngyCoopLoginBtn" value="Mkyong" />
		<property name="name" value="Mkyong" />
		<property name="name" value="Mkyong" />
		<property name="name" value="Mkyong" />
	</bean>

</beans>